capa/__init__.py
capa/_version.py
capa/py.typed
capa/_internal/__init__.py
capa/_internal/adaptive_quality_system.py
capa/_internal/continuous_improvement_system.py
capa/_internal/intelligent_landmark_system.py
capa/_internal/measurement_calibrator.py
capa/_internal/pose_validation_system.py
capa/_internal/suppress_warnings.py
capa/_internal/validation_standards.py
capa/analyzers/__init__.py
capa/analyzers/core_analyzer.py
capa/analyzers/multi_angle_analyzer.py
capa/analyzers/results_integrator.py
capa/modules/__init__.py
capa/modules/forehead_analyzer.py
capa/modules/morphology_analyzer.py
capa/modules/neoclassical_canons.py
capa/modules/wd_analyzer.py
capa_sdk-1.1.0.dist-info/licenses/LICENSE
capa_sdk-1.1.0.dist-info/METADATA
capa_sdk-1.1.0.dist-info/WHEEL
capa_sdk-1.1.0.dist-info/top_level.txt
capa_sdk-1.1.0.dist-info/RECORD
