Metadata-Version: 2.4
Name: capa-sdk
Version: 1.1.0
Summary: CAPA - Craniofacial Analysis & Prediction Architecture SDK
Author: CAPA Team
License: Proprietary - Dual License (Non-Commercial Free / Commercial Paid)
Project-URL: Homepage, https://github.com/yarel2l/capa-sdk
Project-URL: Documentation, https://github.com/yarel2l/capa-sdk#readme
Project-URL: Repository, https://github.com/yarel2l/capa-sdk
Project-URL: Issues, https://github.com/yarel2l/capa-sdk/issues
Keywords: craniofacial,facial-analysis,biometrics,computer-vision,machine-learning
Classifier: Development Status :: 4 - Beta
Classifier: Intended Audience :: Developers
Classifier: Intended Audience :: Science/Research
Classifier: License :: Other/Proprietary License
Classifier: Operating System :: OS Independent
Classifier: Programming Language :: Python :: 3
Classifier: Programming Language :: Python :: 3.9
Classifier: Programming Language :: Python :: 3.10
Classifier: Programming Language :: Python :: 3.11
Classifier: Programming Language :: Python :: 3.12
Classifier: Topic :: Scientific/Engineering :: Image Processing
Classifier: Topic :: Scientific/Engineering :: Artificial Intelligence
Classifier: Typing :: Typed
Requires-Python: >=3.9
License-File: LICENSE
Requires-Dist: numpy>=1.21.0
Requires-Dist: opencv-python>=4.5.0
Requires-Dist: dlib>=19.22.0
Requires-Dist: mediapipe>=0.10.0
Requires-Dist: face-recognition>=1.3.0
Requires-Dist: scikit-learn>=1.0.0
Requires-Dist: scipy>=1.7.0
Requires-Dist: Pillow>=10.0.0
Requires-Dist: matplotlib>=3.5.0
Provides-Extra: dev
Requires-Dist: pytest>=7.0.0; extra == "dev"
Requires-Dist: pytest-cov>=4.0.0; extra == "dev"
Requires-Dist: black>=23.0.0; extra == "dev"
Requires-Dist: isort>=5.12.0; extra == "dev"
Requires-Dist: mypy>=1.0.0; extra == "dev"
Requires-Dist: ruff>=0.1.0; extra == "dev"
Dynamic: license-file
